mcp_server_plaid/__init__.py
mcp_server_plaid/__main__.py
mcp_server_plaid/server.py
mcp_server_plaid/clients/__init__.py
mcp_server_plaid/clients/bill.py
mcp_server_plaid/tools/__init__.py
mcp_server_plaid/tools/registry.py
mcp_server_plaid/tools/tool_get_sandbox_access_token.py
mcp_server_plaid/tools/tool_search_documentation.py
mcp_server_plaid/tools/pfm/__init__.py
mcp_server_plaid/tools/pfm/tool_get_mock_data_prompt.py
mcp_server_plaid/tools/pfm/tool_simulate_webhook.py
mcp_server_plaid-0.1.0.dist-info/METADATA
mcp_server_plaid-0.1.0.dist-info/WHEEL
mcp_server_plaid-0.1.0.dist-info/entry_points.txt
mcp_server_plaid-0.1.0.dist-info/RECORD
