Metadata-Version: 2.4
Name: mcp-server-plaid
Version: 0.1.0
Summary: Model Context Protocol (MCP) server to build fast integration testing with Plaid Sandbox data.
Author-email: "Plaid Inc." <developers@plaid.com>
License: MIT
Requires-Python: >=3.11
Requires-Dist: httpx
Requires-Dist: mcp
Requires-Dist: plaid-python
Requires-Dist: websockets
Provides-Extra: test
Requires-Dist: pytest-asyncio>=0.21.0; extra == 'test'
Requires-Dist: pytest-cov>=4.1.0; extra == 'test'
Requires-Dist: pytest>=7.0.0; extra == 'test'
